Pycasia-0.2.dist-info/DESCRIPTION.rst
Pycasia-0.2.dist-info/METADATA
Pycasia-0.2.dist-info/RECORD
Pycasia-0.2.dist-info/WHEEL
Pycasia-0.2.dist-info/metadata.json
Pycasia-0.2.dist-info/top_level.txt
pycasia/CASIA.py
pycasia/__init__.py
pycasia/statusbar.py
